{
  "model": [
    {
      "vid": 5120,
      "pid": 1180,
      "deviceTypeId": 269,
      "productName": "UA-SmartLight",
      "productLabel": "UA-SmartLight-M05X-3C",
      "partNumber": "M05X-3C",
      "commissioningCustomFlow": 0,
      "commissioningCustomFlowUrl": "",
      "commissioningModeInitialStepsHint": 0,
      "commissioningModeInitialStepsInstruction": "",
      "commissioningModeSecondaryStepsHint": 0,
      "commissioningModeSecondaryStepsInstruction": "",
      "userManualUrl": "",
      "supportUrl": "",
      "productUrl": "",
      "lsfUrl": "",
      "lsfRevision": 0,
      "creator": "cosmos1ynw4zl6xqnvh5zhzhhpxjc6kt8z8wvxkp8edsw"
    },
    {
      "vid": 5120,
      "pid": 1181,
      "deviceTypeId": 269,
      "productName": "UA-SmartLight",
      "productLabel": "UA-SmartLight-M05X-3D",
      "partNumber": "M05X-3D",
      "commissioningCustomFlow": 0,
      "commissioningCustomFlowUrl": "",
      "commissioningModeInitialStepsHint": 0,
      "commissioningModeInitialStepsInstruction": "",
      "commissioningModeSecondaryStepsHint": 0,
      "commissioningModeSecondaryStepsInstruction": "",
      "userManualUrl": "",
      "supportUrl": "",
      "productUrl": "",
      "lsfUrl": "",
      "lsfRevision": 0,
      "creator": "cosmos1ynw4zl6xqnvh5zhzhhpxjc6kt8z8wvxkp8edsw"
    },
    {
      "vid": 5120,
      "pid": 1182,
      "deviceTypeId": 269,
      "productName": "UA-SmartLight",
      "productLabel": "UA-SmartLight-M05X-3E",
      "partNumber": "M05X-3E",
      "commissioningCustomFlow": 0,
      "commissioningCustomFlowUrl": "",
      "commissioningModeInitialStepsHint": 0,
      "commissioningModeInitialStepsInstruction": "",
      "commissioningModeSecondaryStepsHint": 0,
      "commissioningModeSecondaryStepsInstruction": "",
      "userManualUrl": "",
      "supportUrl": "",
      "productUrl": "",
      "lsfUrl": "",
      "lsfRevision": 0,
      "creator": "cosmos1ynw4zl6xqnvh5zhzhhpxjc6kt8z8wvxkp8edsw"
    },
    {
      "vid": 5120,
      "pid": 1183,
      "deviceTypeId": 269,
      "productName": "UA-SmartLight",
      "productLabel": "UA-SmartLight-M05X-3F",
      "partNumber": "M05X-3F",
      "commissioningCustomFlow": 0,
      "commissioningCustomFlowUrl": "",
      "commissioningModeInitialStepsHint": 0,
      "commissioningModeInitialStepsInstruction": "",
      "commissioningModeSecondaryStepsHint": 0,
      "commissioningModeSecondaryStepsInstruction": "",
      "userManualUrl": "",
      "supportUrl": "",
      "productUrl": "",
      "lsfUrl": "",
      "lsfRevision": 0,
      "creator": "cosmos1ynw4zl6xqnvh5zhzhhpxjc6kt8z8wvxkp8edsw"
    },
    {
      "vid": 5120,
      "pid": 1248,
      "deviceTypeId": 266,
      "productName": "Smart Home Plug",
      "productLabel": "M05X-P-01",
      "partNumber": "M05X-P-01",
      "commissioningCustomFlow": 0,
      "commissioningCustomFlowUrl": "",
      "commissioningModeInitialStepsHint": 0,
      "commissioningModeInitialStepsInstruction": "",
      "commissioningModeSecondaryStepsHint": 0,
      "commissioningModeSecondaryStepsInstruction": "",
      "userManualUrl": "",
      "supportUrl": "",
      "productUrl": "",
      "lsfUrl": "",
      "lsfRevision": 0,
      "creator": "cosmos1ynw4zl6xqnvh5zhzhhpxjc6kt8z8wvxkp8edsw"
    },
    {
      "vid": 5120,
      "pid": 1249,
      "deviceTypeId": 266,
      "productName": "Smart Home Plug",
      "productLabel": "M05X-P-02",
      "partNumber": "M05X-P-02",
      "commissioningCustomFlow": 0,
      "commissioningCustomFlowUrl": "",
      "commissioningModeInitialStepsHint": 0,
      "commissioningModeInitialStepsInstruction": "",
      "commissioningModeSecondaryStepsHint": 0,
      "commissioningModeSecondaryStepsInstruction": "",
      "userManualUrl": "",
      "supportUrl": "",
      "productUrl": "",
      "lsfUrl": "",
      "lsfRevision": 0,
      "creator": "cosmos1ynw4zl6xqnvh5zhzhhpxjc6kt8z8wvxkp8edsw"
    },
    {
      "vid": 5120,
      "pid": 1250,
      "deviceTypeId": 266,
      "productName": "Smart Home Plug",
      "productLabel": "M05X-P-03",
      "partNumber": "M05X-P-03",
      "commissioningCustomFlow": 0,
      "commissioningCustomFlowUrl": "",
      "commissioningModeInitialStepsHint": 0,
      "commissioningModeInitialStepsInstruction": "",
      "commissioningModeSecondaryStepsHint": 0,
      "commissioningModeSecondaryStepsInstruction": "",
      "userManualUrl": "",
      "supportUrl": "",
      "productUrl": "",
      "lsfUrl": "",
      "lsfRevision": 0,
      "creator": "cosmos1ynw4zl6xqnvh5zhzhhpxjc6kt8z8wvxkp8edsw"
    },
    {
      "vid": 5120,
      "pid": 1251,
      "deviceTypeId": 266,
      "productName": "Smart Home Plug",
      "productLabel": "M05X-P-04",
      "partNumber": "M05X-P-04",
      "commissioningCustomFlow": 0,
      "commissioningCustomFlowUrl": "",
      "commissioningModeInitialStepsHint": 0,
      "commissioningModeInitialStepsInstruction": "",
      "commissioningModeSecondaryStepsHint": 0,
      "commissioningModeSecondaryStepsInstruction": "",
      "userManualUrl": "",
      "supportUrl": "",
      "productUrl": "",
      "lsfUrl": "",
      "lsfRevision": 0,
      "creator": "cosmos1ynw4zl6xqnvh5zhzhhpxjc6kt8z8wvxkp8edsw"
    },
    {
      "vid": 5120,
      "pid": 1252,
      "deviceTypeId": 266,
      "productName": "Smart Home Plug",
      "productLabel": "M05X-P-05",
      "partNumber": "M05X-P-05",
      "commissioningCustomFlow": 0,
      "commissioningCustomFlowUrl": "",
      "commissioningModeInitialStepsHint": 0,
      "commissioningModeInitialStepsInstruction": "",
      "commissioningModeSecondaryStepsHint": 0,
      "commissioningModeSecondaryStepsInstruction": "",
      "userManualUrl": "",
      "supportUrl": "",
      "productUrl": "",
      "lsfUrl": "",
      "lsfRevision": 0,
      "creator": "cosmos1ynw4zl6xqnvh5zhzhhpxjc6kt8z8wvxkp8edsw"
    },
    {
      "vid": 5120,
      "pid": 1253,
      "deviceTypeId": 266,
      "productName": "Smart Home Plug",
      "productLabel": "M05X-P-06",
      "partNumber": "M05X-P-06",
      "commissioningCustomFlow": 0,
      "commissioningCustomFlowUrl": "",
      "commissioningModeInitialStepsHint": 0,
      "commissioningModeInitialStepsInstruction": "",
      "commissioningModeSecondaryStepsHint": 0,
      "commissioningModeSecondaryStepsInstruction": "",
      "userManualUrl": "",
      "supportUrl": "",
      "productUrl": "",
      "lsfUrl": "",
      "lsfRevision": 0,
      "creator": "cosmos1ynw4zl6xqnvh5zhzhhpxjc6kt8z8wvxkp8edsw"
    },
    {
      "vid": 5120,
      "pid": 1254,
      "deviceTypeId": 266,
      "productName": "Smart Home Plug",
      "productLabel": "M05X-P-07",
      "partNumber": "M05X-P-07",
      "commissioningCustomFlow": 0,
      "commissioningCustomFlowUrl": "",
      "commissioningModeInitialStepsHint": 0,
      "commissioningModeInitialStepsInstruction": "",
      "commissioningModeSecondaryStepsHint": 0,
      "commissioningModeSecondaryStepsInstruction": "",
      "userManualUrl": "",
      "supportUrl": "",
      "productUrl": "",
      "lsfUrl": "",
      "lsfRevision": 0,
      "creator": "cosmos1ynw4zl6xqnvh5zhzhhpxjc6kt8z8wvxkp8edsw"
    },
    {
      "vid": 5120,
      "pid": 1255,
      "deviceTypeId": 266,
      "productName": "Smart Home Plug",
      "productLabel": "M05X-P-08",
      "partNumber": "M05X-P-08",
      "commissioningCustomFlow": 0,
      "commissioningCustomFlowUrl": "",
      "commissioningModeInitialStepsHint": 0,
      "commissioningModeInitialStepsInstruction": "",
      "commissioningModeSecondaryStepsHint": 0,
      "commissioningModeSecondaryStepsInstruction": "",
      "userManualUrl": "",
      "supportUrl": "",
      "productUrl": "",
      "lsfUrl": "",
      "lsfRevision": 0,
      "creator": "cosmos1ynw4zl6xqnvh5zhzhhpxjc6kt8z8wvxkp8edsw"
    },
    {
      "vid": 5120,
      "pid": 1256,
      "deviceTypeId": 266,
      "productName": "Smart Home Plug",
      "productLabel": "M05X-P-09",
      "partNumber": "M05X-P-09",
      "commissioningCustomFlow": 0,
      "commissioningCustomFlowUrl": "",
      "commissioningModeInitialStepsHint": 0,
      "commissioningModeInitialStepsInstruction": "",
      "commissioningModeSecondaryStepsHint": 0,
      "commissioningModeSecondaryStepsInstruction": "",
      "userManualUrl": "",
      "supportUrl": "",
      "productUrl": "",
      "lsfUrl": "",
      "lsfRevision": 0,
      "creator": "cosmos1ynw4zl6xqnvh5zhzhhpxjc6kt8z8wvxkp8edsw"
    },
    {
      "vid": 5120,
      "pid": 1257,
      "deviceTypeId": 266,
      "productName": "Smart Home Plug",
      "productLabel": "M05X-P-0A",
      "partNumber": "M05X-P-0A",
      "commissioningCustomFlow": 0,
      "commissioningCustomFlowUrl": "",
      "commissioningModeInitialStepsHint": 0,
      "commissioningModeInitialStepsInstruction": "",
      "commissioningModeSecondaryStepsHint": 0,
      "commissioningModeSecondaryStepsInstruction": "",
      "userManualUrl": "",
      "supportUrl": "",
      "productUrl": "",
      "lsfUrl": "",
      "lsfRevision": 0,
      "creator": "cosmos1ynw4zl6xqnvh5zhzhhpxjc6kt8z8wvxkp8edsw"
    },
    {
      "vid": 5120,
      "pid": 1258,
      "deviceTypeId": 266,
      "productName": "Smart Home Plug",
      "productLabel": "M05X-P-0B",
      "partNumber": "M05X-P-0B",
      "commissioningCustomFlow": 0,
      "commissioningCustomFlowUrl": "",
      "commissioningModeInitialStepsHint": 0,
      "commissioningModeInitialStepsInstruction": "",
      "commissioningModeSecondaryStepsHint": 0,
      "commissioningModeSecondaryStepsInstruction": "",
      "userManualUrl": "",
      "supportUrl": "",
      "productUrl": "",
      "lsfUrl": "",
      "lsfRevision": 0,
      "creator": "cosmos1ynw4zl6xqnvh5zhzhhpxjc6kt8z8wvxkp8edsw"
    },
    {
      "vid": 5120,
      "pid": 1259,
      "deviceTypeId": 266,
      "productName": "Smart Home Plug",
      "productLabel": "M05X-P-0C",
      "partNumber": "M05X-P-0C",
      "commissioningCustomFlow": 0,
      "commissioningCustomFlowUrl": "",
      "commissioningModeInitialStepsHint": 0,
      "commissioningModeInitialStepsInstruction": "",
      "commissioningModeSecondaryStepsHint": 0,
      "commissioningModeSecondaryStepsInstruction": "",
      "userManualUrl": "",
      "supportUrl": "",
      "productUrl": "",
      "lsfUrl": "",
      "lsfRevision": 0,
      "creator": "cosmos1ynw4zl6xqnvh5zhzhhpxjc6kt8z8wvxkp8edsw"
    },
    {
      "vid": 5120,
      "pid": 1260,
      "deviceTypeId": 266,
      "productName": "Smart Home Plug",
      "productLabel": "M05X-P-0D",
      "partNumber": "M05X-P-0D",
      "commissioningCustomFlow": 0,
      "commissioningCustomFlowUrl": "",
      "commissioningModeInitialStepsHint": 0,
      "commissioningModeInitialStepsInstruction": "",
      "commissioningModeSecondaryStepsHint": 0,
      "commissioningModeSecondaryStepsInstruction": "",
      "userManualUrl": "",
      "supportUrl": "",
      "productUrl": "",
      "lsfUrl": "",
      "lsfRevision": 0,
      "creator": "cosmos1ynw4zl6xqnvh5zhzhhpxjc6kt8z8wvxkp8edsw"
    },
    {
      "vid": 5120,
      "pid": 1261,
      "deviceTypeId": 266,
      "productName": "Smart Home Plug",
      "productLabel": "M05X-P-0E",
      "partNumber": "M05X-P-0E",
      "commissioningCustomFlow": 0,
      "commissioningCustomFlowUrl": "",
      "commissioningModeInitialStepsHint": 0,
      "commissioningModeInitialStepsInstruction": "",
      "commissioningModeSecondaryStepsHint": 0,
      "commissioningModeSecondaryStepsInstruction": "",
      "userManualUrl": "",
      "supportUrl": "",
      "productUrl": "",
      "lsfUrl": "",
      "lsfRevision": 0,
      "creator": "cosmos1ynw4zl6xqnvh5zhzhhpxjc6kt8z8wvxkp8edsw"
    },
    {
      "vid": 5120,
      "pid": 1262,
      "deviceTypeId": 266,
      "productName": "Smart Home Plug",
      "productLabel": "M05X-P-0F",
      "partNumber": "M05X-P-0F",
      "commissioningCustomFlow": 0,
      "commissioningCustomFlowUrl": "",
      "commissioningModeInitialStepsHint": 0,
      "commissioningModeInitialStepsInstruction": "",
      "commissioningModeSecondaryStepsHint": 0,
      "commissioningModeSecondaryStepsInstruction": "",
      "userManualUrl": "",
      "supportUrl": "",
      "productUrl": "",
      "lsfUrl": "",
      "lsfRevision": 0,
      "creator": "cosmos1ynw4zl6xqnvh5zhzhhpxjc6kt8z8wvxkp8edsw"
    },
    {
      "vid": 5120,
      "pid": 1263,
      "deviceTypeId": 266,
      "productName": "Smart Home Plug",
      "productLabel": "M05X-P-10",
      "partNumber": "M05X-P-10",
      "commissioningCustomFlow": 0,
      "commissioningCustomFlowUrl": "",
      "commissioningModeInitialStepsHint": 0,
      "commissioningModeInitialStepsInstruction": "",
      "commissioningModeSecondaryStepsHint": 0,
      "commissioningModeSecondaryStepsInstruction": "",
      "userManualUrl": "",
      "supportUrl": "",
      "productUrl": "",
      "lsfUrl": "",
      "lsfRevision": 0,
      "creator": "cosmos1ynw4zl6xqnvh5zhzhhpxjc6kt8z8wvxkp8edsw"
    },
    {
      "vid": 5120,
      "pid": 1264,
      "deviceTypeId": 266,
      "productName": "Smart Home Plug",
      "productLabel": "M05X-P-11",
      "partNumber": "M05X-P-11",
      "commissioningCustomFlow": 0,
      "commissioningCustomFlowUrl": "",
      "commissioningModeInitialStepsHint": 0,
      "commissioningModeInitialStepsInstruction": "",
      "commissioningModeSecondaryStepsHint": 0,
      "commissioningModeSecondaryStepsInstruction": "",
      "userManualUrl": "",
      "supportUrl": "",
      "productUrl": "",
      "lsfUrl": "",
      "lsfRevision": 0,
      "creator": "cosmos1ynw4zl6xqnvh5zhzhhpxjc6kt8z8wvxkp8edsw"
    },
    {
      "vid": 5120,
      "pid": 1265,
      "deviceTypeId": 266,
      "productName": "Smart Home Plug",
      "productLabel": "M05X-P-12",
      "partNumber": "M05X-P-12",
      "commissioningCustomFlow": 0,
      "commissioningCustomFlowUrl": "",
      "commissioningModeInitialStepsHint": 0,
      "commissioningModeInitialStepsInstruction": "",
      "commissioningModeSecondaryStepsHint": 0,
      "commissioningModeSecondaryStepsInstruction": "",
      "userManualUrl": "",
      "supportUrl": "",
      "productUrl": "",
      "lsfUrl": "",
      "lsfRevision": 0,
      "creator": "cosmos1ynw4zl6xqnvh5zhzhhpxjc6kt8z8wvxkp8edsw"
    },
    {
      "vid": 5120,
      "pid": 1266,
      "deviceTypeId": 266,
      "productName": "Smart Home Plug",
      "productLabel": "M05X-P-13",
      "partNumber": "M05X-P-13",
      "commissioningCustomFlow": 0,
      "commissioningCustomFlowUrl": "",
      "commissioningModeInitialStepsHint": 0,
      "commissioningModeInitialStepsInstruction": "",
      "commissioningModeSecondaryStepsHint": 0,
      "commissioningModeSecondaryStepsInstruction": "",
      "userManualUrl": "",
      "supportUrl": "",
      "productUrl": "",
      "lsfUrl": "",
      "lsfRevision": 0,
      "creator": "cosmos1ynw4zl6xqnvh5zhzhhpxjc6kt8z8wvxkp8edsw"
    },
    {
      "vid": 5120,
      "pid": 1267,
      "deviceTypeId": 266,
      "productName": "Smart Home Plug",
      "productLabel": "M05X-P-14",
      "partNumber": "M05X-P-14",
      "commissioningCustomFlow": 0,
      "commissioningCustomFlowUrl": "",
      "commissioningModeInitialStepsHint": 0,
      "commissioningModeInitialStepsInstruction": "",
      "commissioningModeSecondaryStepsHint": 0,
      "commissioningModeSecondaryStepsInstruction": "",
      "userManualUrl": "",
      "supportUrl": "",
      "productUrl": "",
      "lsfUrl": "",
      "lsfRevision": 0,
      "creator": "cosmos1ynw4zl6xqnvh5zhzhhpxjc6kt8z8wvxkp8edsw"
    },
    {
      "vid": 5120,
      "pid": 1268,
      "deviceTypeId": 266,
      "productName": "Smart Home Plug",
      "productLabel": "M05X-P-15",
      "partNumber": "M05X-P-15",
      "commissioningCustomFlow": 0,
      "commissioningCustomFlowUrl": "",
      "commissioningModeInitialStepsHint": 0,
      "commissioningModeInitialStepsInstruction": "",
      "commissioningModeSecondaryStepsHint": 0,
      "commissioningModeSecondaryStepsInstruction": "",
      "userManualUrl": "",
      "supportUrl": "",
      "productUrl": "",
      "lsfUrl": "",
      "lsfRevision": 0,
      "creator": "cosmos1ynw4zl6xqnvh5zhzhhpxjc6kt8z8wvxkp8edsw"
    },
    {
      "vid": 5120,
      "pid": 1269,
      "deviceTypeId": 266,
      "productName": "Smart Home Plug",
      "productLabel": "M05X-P-16",
      "partNumber": "M05X-P-16",
      "commissioningCustomFlow": 0,
      "commissioningCustomFlowUrl": "",
      "commissioningModeInitialStepsHint": 0,
      "commissioningModeInitialStepsInstruction": "",
      "commissioningModeSecondaryStepsHint": 0,
      "commissioningModeSecondaryStepsInstruction": "",
      "userManualUrl": "",
      "supportUrl": "",
      "productUrl": "",
      "lsfUrl": "",
      "lsfRevision": 0,
      "creator": "cosmos1ynw4zl6xqnvh5zhzhhpxjc6kt8z8wvxkp8edsw"
    },
    {
      "vid": 5120,
      "pid": 1270,
      "deviceTypeId": 266,
      "productName": "Smart Home Plug",
      "productLabel": "M05X-P-17",
      "partNumber": "M05X-P-17",
      "commissioningCustomFlow": 0,
      "commissioningCustomFlowUrl": "",
      "commissioningModeInitialStepsHint": 0,
      "commissioningModeInitialStepsInstruction": "",
      "commissioningModeSecondaryStepsHint": 0,
      "commissioningModeSecondaryStepsInstruction": "",
      "userManualUrl": "",
      "supportUrl": "",
      "productUrl": "",
      "lsfUrl": "",
      "lsfRevision": 0,
      "creator": "cosmos1ynw4zl6xqnvh5zhzhhpxjc6kt8z8wvxkp8edsw"
    },
    {
      "vid": 5120,
      "pid": 1271,
      "deviceTypeId": 266,
      "productName": "Smart Home Plug",
      "productLabel": "M05X-P-18",
      "partNumber": "M05X-P-18",
      "commissioningCustomFlow": 0,
      "commissioningCustomFlowUrl": "",
      "commissioningModeInitialStepsHint": 0,
      "commissioningModeInitialStepsInstruction": "",
      "commissioningModeSecondaryStepsHint": 0,
      "commissioningModeSecondaryStepsInstruction": "",
      "userManualUrl": "",
      "supportUrl": "",
      "productUrl": "",
      "lsfUrl": "",
      "lsfRevision": 0,
      "creator": "cosmos1ynw4zl6xqnvh5zhzhhpxjc6kt8z8wvxkp8edsw"
    },
    {
      "vid": 5120,
      "pid": 1272,
      "deviceTypeId": 266,
      "productName": "Smart Home Plug",
      "productLabel": "M05X-P-19",
      "partNumber": "M05X-P-19",
      "commissioningCustomFlow": 0,
      "commissioningCustomFlowUrl": "",
      "commissioningModeInitialStepsHint": 0,
      "commissioningModeInitialStepsInstruction": "",
      "commissioningModeSecondaryStepsHint": 0,
      "commissioningModeSecondaryStepsInstruction": "",
      "userManualUrl": "",
      "supportUrl": "",
      "productUrl": "",
      "lsfUrl": "",
      "lsfRevision": 0,
      "creator": "cosmos1ynw4zl6xqnvh5zhzhhpxjc6kt8z8wvxkp8edsw"
    },
    {
      "vid": 5120,
      "pid": 1273,
      "deviceTypeId": 266,
      "productName": "Smart Home Plug",
      "productLabel": "M05X-P-1A",
      "partNumber": "M05X-P-1A",
      "commissioningCustomFlow": 0,
      "commissioningCustomFlowUrl": "",
      "commissioningModeInitialStepsHint": 0,
      "commissioningModeInitialStepsInstruction": "",
      "commissioningModeSecondaryStepsHint": 0,
      "commissioningModeSecondaryStepsInstruction": "",
      "userManualUrl": "",
      "supportUrl": "",
      "productUrl": "",
      "lsfUrl": "",
      "lsfRevision": 0,
      "creator": "cosmos1ynw4zl6xqnvh5zhzhhpxjc6kt8z8wvxkp8edsw"
    },
    {
      "vid": 5120,
      "pid": 1274,
      "deviceTypeId": 266,
      "productName": "Smart Home Plug",
      "productLabel": "M05X-P-1B",
      "partNumber": "M05X-P-1B",
      "commissioningCustomFlow": 0,
      "commissioningCustomFlowUrl": "",
      "commissioningModeInitialStepsHint": 0,
      "commissioningModeInitialStepsInstruction": "",
      "commissioningModeSecondaryStepsHint": 0,
      "commissioningModeSecondaryStepsInstruction": "",
      "userManualUrl": "",
      "supportUrl": "",
      "productUrl": "",
      "lsfUrl": "",
      "lsfRevision": 0,
      "creator": "cosmos1ynw4zl6xqnvh5zhzhhpxjc6kt8z8wvxkp8edsw"
    },
    {
      "vid": 5120,
      "pid": 1275,
      "deviceTypeId": 266,
      "productName": "Smart Home Plug",
      "productLabel": "M05X-P-1C",
      "partNumber": "M05X-P-1C",
      "commissioningCustomFlow": 0,
      "commissioningCustomFlowUrl": "",
      "commissioningModeInitialStepsHint": 0,
      "commissioningModeInitialStepsInstruction": "",
      "commissioningModeSecondaryStepsHint": 0,
      "commissioningModeSecondaryStepsInstruction": "",
      "userManualUrl": "",
      "supportUrl": "",
      "productUrl": "",
      "lsfUrl": "",
      "lsfRevision": 0,
      "creator": "cosmos1ynw4zl6xqnvh5zhzhhpxjc6kt8z8wvxkp8edsw"
    },
    {
      "vid": 5120,
      "pid": 1276,
      "deviceTypeId": 266,
      "productName": "Smart Home Plug",
      "productLabel": "M05X-P-1D",
      "partNumber": "M05X-P-1D",
      "commissioningCustomFlow": 0,
      "commissioningCustomFlowUrl": "",
      "commissioningModeInitialStepsHint": 0,
      "commissioningModeInitialStepsInstruction": "",
      "commissioningModeSecondaryStepsHint": 0,
      "commissioningModeSecondaryStepsInstruction": "",
      "userManualUrl": "",
      "supportUrl": "",
      "productUrl": "",
      "lsfUrl": "",
      "lsfRevision": 0,
      "creator": "cosmos1ynw4zl6xqnvh5zhzhhpxjc6kt8z8wvxkp8edsw"
    },
    {
      "vid": 5120,
      "pid": 1277,
      "deviceTypeId": 266,
      "productName": "Smart Home Plug",
      "productLabel": "M05X-P-1E",
      "partNumber": "M05X-P-1E",
      "commissioningCustomFlow": 0,
      "commissioningCustomFlowUrl": "",
      "commissioningModeInitialStepsHint": 0,
      "commissioningModeInitialStepsInstruction": "",
      "commissioningModeSecondaryStepsHint": 0,
      "commissioningModeSecondaryStepsInstruction": "",
      "userManualUrl": "",
      "supportUrl": "",
      "productUrl": "",
      "lsfUrl": "",
      "lsfRevision": 0,
      "creator": "cosmos1ynw4zl6xqnvh5zhzhhpxjc6kt8z8wvxkp8edsw"
    },
    {
      "vid": 5120,
      "pid": 1278,
      "deviceTypeId": 266,
      "productName": "Smart Home Plug",
      "productLabel": "M05X-P-1F",
      "partNumber": "M05X-P-1F",
      "commissioningCustomFlow": 0,
      "commissioningCustomFlowUrl": "",
      "commissioningModeInitialStepsHint": 0,
      "commissioningModeInitialStepsInstruction": "",
      "commissioningModeSecondaryStepsHint": 0,
      "commissioningModeSecondaryStepsInstruction": "",
      "userManualUrl": "",
      "supportUrl": "",
      "productUrl": "",
      "lsfUrl": "",
      "lsfRevision": 0,
      "creator": "cosmos1ynw4zl6xqnvh5zhzhhpxjc6kt8z8wvxkp8edsw"
    },
    {
      "vid": 5120,
      "pid": 1279,
      "deviceTypeId": 266,
      "productName": "Smart Home Plug",
      "productLabel": "M05X-P-20",
      "partNumber": "M05X-P-20",
      "commissioningCustomFlow": 0,
      "commissioningCustomFlowUrl": "",
      "commissioningModeInitialStepsHint": 0,
      "commissioningModeInitialStepsInstruction": "",
      "commissioningModeSecondaryStepsHint": 0,
      "commissioningModeSecondaryStepsInstruction": "",
      "userManualUrl": "",
      "supportUrl": "",
      "productUrl": "",
      "lsfUrl": "",
      "lsfRevision": 0,
      "creator": "cosmos1ynw4zl6xqnvh5zhzhhpxjc6kt8z8wvxkp8edsw"
    },
    {
      "vid": 5120,
      "pid": 1280,
      "deviceTypeId": 266,
      "productName": "Smart Home Plug",
      "productLabel": "M05X-P-21",
      "partNumber": "M05X-P-21",
      "commissioningCustomFlow": 0,
      "commissioningCustomFlowUrl": "",
      "commissioningModeInitialStepsHint": 0,
      "commissioningModeInitialStepsInstruction": "",
      "commissioningModeSecondaryStepsHint": 0,
      "commissioningModeSecondaryStepsInstruction": "",
      "userManualUrl": "",
      "supportUrl": "",
      "productUrl": "",
      "lsfUrl": "",
      "lsfRevision": 0,
      "creator": "cosmos1ynw4zl6xqnvh5zhzhhpxjc6kt8z8wvxkp8edsw"
    },
    {
      "vid": 5120,
      "pid": 1281,
      "deviceTypeId": 266,
      "productName": "Smart Home Plug",
      "productLabel": "M05X-P-22",
      "partNumber": "M05X-P-22",
      "commissioningCustomFlow": 0,
      "commissioningCustomFlowUrl": "",
      "commissioningModeInitialStepsHint": 0,
      "commissioningModeInitialStepsInstruction": "",
      "commissioningModeSecondaryStepsHint": 0,
      "commissioningModeSecondaryStepsInstruction": "",
      "userManualUrl": "",
      "supportUrl": "",
      "productUrl": "",
      "lsfUrl": "",
      "lsfRevision": 0,
      "creator": "cosmos1ynw4zl6xqnvh5zhzhhpxjc6kt8z8wvxkp8edsw"
    },
    {
      "vid": 5120,
      "pid": 1282,
      "deviceTypeId": 266,
      "productName": "Smart Home Plug",
      "productLabel": "M05X-P-23",
      "partNumber": "M05X-P-23",
      "commissioningCustomFlow": 0,
      "commissioningCustomFlowUrl": "",
      "commissioningModeInitialStepsHint": 0,
      "commissioningModeInitialStepsInstruction": "",
      "commissioningModeSecondaryStepsHint": 0,
      "commissioningModeSecondaryStepsInstruction": "",
      "userManualUrl": "",
      "supportUrl": "",
      "productUrl": "",
      "lsfUrl": "",
      "lsfRevision": 0,
      "creator": "cosmos1ynw4zl6xqnvh5zhzhhpxjc6kt8z8wvxkp8edsw"
    },
    {
      "vid": 5120,
      "pid": 1283,
      "deviceTypeId": 266,
      "productName": "Smart Home Plug",
      "productLabel": "M05X-P-24",
      "partNumber": "M05X-P-24",
      "commissioningCustomFlow": 0,
      "commissioningCustomFlowUrl": "",
      "commissioningModeInitialStepsHint": 0,
      "commissioningModeInitialStepsInstruction": "",
      "commissioningModeSecondaryStepsHint": 0,
      "commissioningModeSecondaryStepsInstruction": "",
      "userManualUrl": "",
      "supportUrl": "",
      "productUrl": "",
      "lsfUrl": "",
      "lsfRevision": 0,
      "creator": "cosmos1ynw4zl6xqnvh5zhzhhpxjc6kt8z8wvxkp8edsw"
    },
    {
      "vid": 5120,
      "pid": 1284,
      "deviceTypeId": 266,
      "productName": "Smart Home Plug",
      "productLabel": "M05X-P-25",
      "partNumber": "M05X-P-25",
      "commissioningCustomFlow": 0,
      "commissioningCustomFlowUrl": "",
      "commissioningModeInitialStepsHint": 0,
      "commissioningModeInitialStepsInstruction": "",
      "commissioningModeSecondaryStepsHint": 0,
      "commissioningModeSecondaryStepsInstruction": "",
      "userManualUrl": "",
      "supportUrl": "",
      "productUrl": "",
      "lsfUrl": "",
      "lsfRevision": 0,
      "creator": "cosmos1ynw4zl6xqnvh5zhzhhpxjc6kt8z8wvxkp8edsw"
    },
    {
      "vid": 5120,
      "pid": 1285,
      "deviceTypeId": 266,
      "productName": "Smart Home Plug",
      "productLabel": "M05X-P-26",
      "partNumber": "M05X-P-26",
      "commissioningCustomFlow": 0,
      "commissioningCustomFlowUrl": "",
      "commissioningModeInitialStepsHint": 0,
      "commissioningModeInitialStepsInstruction": "",
      "commissioningModeSecondaryStepsHint": 0,
      "commissioningModeSecondaryStepsInstruction": "",
      "userManualUrl": "",
      "supportUrl": "",
      "productUrl": "",
      "lsfUrl": "",
      "lsfRevision": 0,
      "creator": "cosmos1ynw4zl6xqnvh5zhzhhpxjc6kt8z8wvxkp8edsw"
    },
    {
      "vid": 5120,
      "pid": 1286,
      "deviceTypeId": 266,
      "productName": "Smart Home Plug",
      "productLabel": "M05X-P-27",
      "partNumber": "M05X-P-27",
      "commissioningCustomFlow": 0,
      "commissioningCustomFlowUrl": "",
      "commissioningModeInitialStepsHint": 0,
      "commissioningModeInitialStepsInstruction": "",
      "commissioningModeSecondaryStepsHint": 0,
      "commissioningModeSecondaryStepsInstruction": "",
      "userManualUrl": "",
      "supportUrl": "",
      "productUrl": "",
      "lsfUrl": "",
      "lsfRevision": 0,
      "creator": "cosmos1ynw4zl6xqnvh5zhzhhpxjc6kt8z8wvxkp8edsw"
    },
    {
      "vid": 5120,
      "pid": 1287,
      "deviceTypeId": 266,
      "productName": "Smart Home Plug",
      "productLabel": "M05X-P-28",
      "partNumber": "M05X-P-28",
      "commissioningCustomFlow": 0,
      "commissioningCustomFlowUrl": "",
      "commissioningModeInitialStepsHint": 0,
      "commissioningModeInitialStepsInstruction": "",
      "commissioningModeSecondaryStepsHint": 0,
      "commissioningModeSecondaryStepsInstruction": "",
      "userManualUrl": "",
      "supportUrl": "",
      "productUrl": "",
      "lsfUrl": "",
      "lsfRevision": 0,
      "creator": "cosmos1ynw4zl6xqnvh5zhzhhpxjc6kt8z8wvxkp8edsw"
    },
    {
      "vid": 5120,
      "pid": 1288,
      "deviceTypeId": 266,
      "productName": "Smart Home Plug",
      "productLabel": "M05X-P-29",
      "partNumber": "M05X-P-29",
      "commissioningCustomFlow": 0,
      "commissioningCustomFlowUrl": "",
      "commissioningModeInitialStepsHint": 0,
      "commissioningModeInitialStepsInstruction": "",
      "commissioningModeSecondaryStepsHint": 0,
      "commissioningModeSecondaryStepsInstruction": "",
      "userManualUrl": "",
      "supportUrl": "",
      "productUrl": "",
      "lsfUrl": "",
      "lsfRevision": 0,
      "creator": "cosmos1ynw4zl6xqnvh5zhzhhpxjc6kt8z8wvxkp8edsw"
    },
    {
      "vid": 5120,
      "pid": 1289,
      "deviceTypeId": 266,
      "productName": "Smart Home Plug",
      "productLabel": "M05X-P-2A",
      "partNumber": "M05X-P-2A",
      "commissioningCustomFlow": 0,
      "commissioningCustomFlowUrl": "",
      "commissioningModeInitialStepsHint": 0,
      "commissioningModeInitialStepsInstruction": "",
      "commissioningModeSecondaryStepsHint": 0,
      "commissioningModeSecondaryStepsInstruction": "",
      "userManualUrl": "",
      "supportUrl": "",
      "productUrl": "",
      "lsfUrl": "",
      "lsfRevision": 0,
      "creator": "cosmos1ynw4zl6xqnvh5zhzhhpxjc6kt8z8wvxkp8edsw"
    },
    {
      "vid": 5120,
      "pid": 1290,
      "deviceTypeId": 266,
      "productName": "Smart Home Plug",
      "productLabel": "M05X-P-2B",
      "partNumber": "M05X-P-2B",
      "commissioningCustomFlow": 0,
      "commissioningCustomFlowUrl": "",
      "commissioningModeInitialStepsHint": 0,
      "commissioningModeInitialStepsInstruction": "",
      "commissioningModeSecondaryStepsHint": 0,
      "commissioningModeSecondaryStepsInstruction": "",
      "userManualUrl": "",
      "supportUrl": "",
      "productUrl": "",
      "lsfUrl": "",
      "lsfRevision": 0,
      "creator": "cosmos1ynw4zl6xqnvh5zhzhhpxjc6kt8z8wvxkp8edsw"
    },
    {
      "vid": 5120,
      "pid": 1291,
      "deviceTypeId": 266,
      "productName": "Smart Home Plug",
      "productLabel": "M05X-P-2C",
      "partNumber": "M05X-P-2C",
      "commissioningCustomFlow": 0,
      "commissioningCustomFlowUrl": "",
      "commissioningModeInitialStepsHint": 0,
      "commissioningModeInitialStepsInstruction": "",
      "commissioningModeSecondaryStepsHint": 0,
      "commissioningModeSecondaryStepsInstruction": "",
      "userManualUrl": "",
      "supportUrl": "",
      "productUrl": "",
      "lsfUrl": "",
      "lsfRevision": 0,
      "creator": "cosmos1ynw4zl6xqnvh5zhzhhpxjc6kt8z8wvxkp8edsw"
    },
    {
      "vid": 5120,
      "pid": 1292,
      "deviceTypeId": 266,
      "productName": "Smart Home Plug",
      "productLabel": "M05X-P-2D",
      "partNumber": "M05X-P-2D",
      "commissioningCustomFlow": 0,
      "commissioningCustomFlowUrl": "",
      "commissioningModeInitialStepsHint": 0,
      "commissioningModeInitialStepsInstruction": "",
      "commissioningModeSecondaryStepsHint": 0,
      "commissioningModeSecondaryStepsInstruction": "",
      "userManualUrl": "",
      "supportUrl": "",
      "productUrl": "",
      "lsfUrl": "",
      "lsfRevision": 0,
      "creator": "cosmos1ynw4zl6xqnvh5zhzhhpxjc6kt8z8wvxkp8edsw"
    },
    {
      "vid": 5120,
      "pid": 1293,
      "deviceTypeId": 266,
      "productName": "Smart Home Plug",
      "productLabel": "M05X-P-2E",
      "partNumber": "M05X-P-2E",
      "commissioningCustomFlow": 0,
      "commissioningCustomFlowUrl": "",
      "commissioningModeInitialStepsHint": 0,
      "commissioningModeInitialStepsInstruction": "",
      "commissioningModeSecondaryStepsHint": 0,
      "commissioningModeSecondaryStepsInstruction": "",
      "userManualUrl": "",
      "supportUrl": "",
      "productUrl": "",
      "lsfUrl": "",
      "lsfRevision": 0,
      "creator": "cosmos1ynw4zl6xqnvh5zhzhhpxjc6kt8z8wvxkp8edsw"
    },
    {
      "vid": 5120,
      "pid": 1294,
      "deviceTypeId": 266,
      "productName": "Smart Home Plug",
      "productLabel": "M05X-P-2F",
      "partNumber": "M05X-P-2F",
      "commissioningCustomFlow": 0,
      "commissioningCustomFlowUrl": "",
      "commissioningModeInitialStepsHint": 0,
      "commissioningModeInitialStepsInstruction": "",
      "commissioningModeSecondaryStepsHint": 0,
      "commissioningModeSecondaryStepsInstruction": "",
      "userManualUrl": "",
      "supportUrl": "",
      "productUrl": "",
      "lsfUrl": "",
      "lsfRevision": 0,
      "creator": "cosmos1ynw4zl6xqnvh5zhzhhpxjc6kt8z8wvxkp8edsw"
    },
    {
      "vid": 5120,
      "pid": 1295,
      "deviceTypeId": 266,
      "productName": "Smart Home Plug",
      "productLabel": "M05X-P-30",
      "partNumber": "M05X-P-30",
      "commissioningCustomFlow": 0,
      "commissioningCustomFlowUrl": "",
      "commissioningModeInitialStepsHint": 0,
      "commissioningModeInitialStepsInstruction": "",
      "commissioningModeSecondaryStepsHint": 0,
      "commissioningModeSecondaryStepsInstruction": "",
      "userManualUrl": "",
      "supportUrl": "",
      "productUrl": "",
      "lsfUrl": "",
      "lsfRevision": 0,
      "creator": "cosmos1ynw4zl6xqnvh5zhzhhpxjc6kt8z8wvxkp8edsw"
    },
    {
      "vid": 5120,
      "pid": 1296,
      "deviceTypeId": 266,
      "productName": "Smart Home Plug",
      "productLabel": "M05X-P-31",
      "partNumber": "M05X-P-31",
      "commissioningCustomFlow": 0,
      "commissioningCustomFlowUrl": "",
      "commissioningModeInitialStepsHint": 0,
      "commissioningModeInitialStepsInstruction": "",
      "commissioningModeSecondaryStepsHint": 0,
      "commissioningModeSecondaryStepsInstruction": "",
      "userManualUrl": "",
      "supportUrl": "",
      "productUrl": "",
      "lsfUrl": "",
      "lsfRevision": 0,
      "creator": "cosmos1ynw4zl6xqnvh5zhzhhpxjc6kt8z8wvxkp8edsw"
    },
    {
      "vid": 5120,
      "pid": 1297,
      "deviceTypeId": 266,
      "productName": "Smart Home Plug",
      "productLabel": "M05X-P-32",
      "partNumber": "M05X-P-32",
      "commissioningCustomFlow": 0,
      "commissioningCustomFlowUrl": "",
      "commissioningModeInitialStepsHint": 0,
      "commissioningModeInitialStepsInstruction": "",
      "commissioningModeSecondaryStepsHint": 0,
      "commissioningModeSecondaryStepsInstruction": "",
      "userManualUrl": "",
      "supportUrl": "",
      "productUrl": "",
      "lsfUrl": "",
      "lsfRevision": 0,
      "creator": "cosmos1ynw4zl6xqnvh5zhzhhpxjc6kt8z8wvxkp8edsw"
    },
    {
      "vid": 5120,
      "pid": 1298,
      "deviceTypeId": 266,
      "productName": "Smart Home Plug",
      "productLabel": "M05X-P-33",
      "partNumber": "M05X-P-33",
      "commissioningCustomFlow": 0,
      "commissioningCustomFlowUrl": "",
      "commissioningModeInitialStepsHint": 0,
      "commissioningModeInitialStepsInstruction": "",
      "commissioningModeSecondaryStepsHint": 0,
      "commissioningModeSecondaryStepsInstruction": "",
      "userManualUrl": "",
      "supportUrl": "",
      "productUrl": "",
      "lsfUrl": "",
      "lsfRevision": 0,
      "creator": "cosmos1ynw4zl6xqnvh5zhzhhpxjc6kt8z8wvxkp8edsw"
    },
    {
      "vid": 5120,
      "pid": 1299,
      "deviceTypeId": 266,
      "productName": "Smart Home Plug",
      "productLabel": "M05X-P-34",
      "partNumber": "M05X-P-34",
      "commissioningCustomFlow": 0,
      "commissioningCustomFlowUrl": "",
      "commissioningModeInitialStepsHint": 0,
      "commissioningModeInitialStepsInstruction": "",
      "commissioningModeSecondaryStepsHint": 0,
      "commissioningModeSecondaryStepsInstruction": "",
      "userManualUrl": "",
      "supportUrl": "",
      "productUrl": "",
      "lsfUrl": "",
      "lsfRevision": 0,
      "creator": "cosmos1ynw4zl6xqnvh5zhzhhpxjc6kt8z8wvxkp8edsw"
    },
    {
      "vid": 5120,
      "pid": 1300,
      "deviceTypeId": 266,
      "productName": "Smart Home Plug",
      "productLabel": "M05X-P-35",
      "partNumber": "M05X-P-35",
      "commissioningCustomFlow": 0,
      "commissioningCustomFlowUrl": "",
      "commissioningModeInitialStepsHint": 0,
      "commissioningModeInitialStepsInstruction": "",
      "commissioningModeSecondaryStepsHint": 0,
      "commissioningModeSecondaryStepsInstruction": "",
      "userManualUrl": "",
      "supportUrl": "",
      "productUrl": "",
      "lsfUrl": "",
      "lsfRevision": 0,
      "creator": "cosmos1ynw4zl6xqnvh5zhzhhpxjc6kt8z8wvxkp8edsw"
    },
    {
      "vid": 5120,
      "pid": 1301,
      "deviceTypeId": 266,
      "productName": "Smart Home Plug",
      "productLabel": "M05X-P-36",
      "partNumber": "M05X-P-36",
      "commissioningCustomFlow": 0,
      "commissioningCustomFlowUrl": "",
      "commissioningModeInitialStepsHint": 0,
      "commissioningModeInitialStepsInstruction": "",
      "commissioningModeSecondaryStepsHint": 0,
      "commissioningModeSecondaryStepsInstruction": "",
      "userManualUrl": "",
      "supportUrl": "",
      "productUrl": "",
      "lsfUrl": "",
      "lsfRevision": 0,
      "creator": "cosmos1ynw4zl6xqnvh5zhzhhpxjc6kt8z8wvxkp8edsw"
    },
    {
      "vid": 5120,
      "pid": 1302,
      "deviceTypeId": 266,
      "productName": "Smart Home Plug",
      "productLabel": "M05X-P-37",
      "partNumber": "M05X-P-37",
      "commissioningCustomFlow": 0,
      "commissioningCustomFlowUrl": "",
      "commissioningModeInitialStepsHint": 0,
      "commissioningModeInitialStepsInstruction": "",
      "commissioningModeSecondaryStepsHint": 0,
      "commissioningModeSecondaryStepsInstruction": "",
      "userManualUrl": "",
      "supportUrl": "",
      "productUrl": "",
      "lsfUrl": "",
      "lsfRevision": 0,
      "creator": "cosmos1ynw4zl6xqnvh5zhzhhpxjc6kt8z8wvxkp8edsw"
    },
    {
      "vid": 5120,
      "pid": 1303,
      "deviceTypeId": 266,
      "productName": "Smart Home Plug",
      "productLabel": "M05X-P-38",
      "partNumber": "M05X-P-38",
      "commissioningCustomFlow": 0,
      "commissioningCustomFlowUrl": "",
      "commissioningModeInitialStepsHint": 0,
      "commissioningModeInitialStepsInstruction": "",
      "commissioningModeSecondaryStepsHint": 0,
      "commissioningModeSecondaryStepsInstruction": "",
      "userManualUrl": "",
      "supportUrl": "",
      "productUrl": "",
      "lsfUrl": "",
      "lsfRevision": 0,
      "creator": "cosmos1ynw4zl6xqnvh5zhzhhpxjc6kt8z8wvxkp8edsw"
    },
    {
      "vid": 5120,
      "pid": 1304,
      "deviceTypeId": 266,
      "productName": "Smart Home Plug",
      "productLabel": "M05X-P-39",
      "partNumber": "M05X-P-39",
      "commissioningCustomFlow": 0,
      "commissioningCustomFlowUrl": "",
      "commissioningModeInitialStepsHint": 0,
      "commissioningModeInitialStepsInstruction": "",
      "commissioningModeSecondaryStepsHint": 0,
      "commissioningModeSecondaryStepsInstruction": "",
      "userManualUrl": "",
      "supportUrl": "",
      "productUrl": "",
      "lsfUrl": "",
      "lsfRevision": 0,
      "creator": "cosmos1ynw4zl6xqnvh5zhzhhpxjc6kt8z8wvxkp8edsw"
    },
    {
      "vid": 5120,
      "pid": 1305,
      "deviceTypeId": 266,
      "productName": "Smart Home Plug",
      "productLabel": "M05X-P-3A",
      "partNumber": "M05X-P-3A",
      "commissioningCustomFlow": 0,
      "commissioningCustomFlowUrl": "",
      "commissioningModeInitialStepsHint": 0,
      "commissioningModeInitialStepsInstruction": "",
      "commissioningModeSecondaryStepsHint": 0,
      "commissioningModeSecondaryStepsInstruction": "",
      "userManualUrl": "",
      "supportUrl": "",
      "productUrl": "",
      "lsfUrl": "",
      "lsfRevision": 0,
      "creator": "cosmos1ynw4zl6xqnvh5zhzhhpxjc6kt8z8wvxkp8edsw"
    },
    {
      "vid": 5120,
      "pid": 1306,
      "deviceTypeId": 266,
      "productName": "Smart Home Plug",
      "productLabel": "M05X-P-3B",
      "partNumber": "M05X-P-3B",
      "commissioningCustomFlow": 0,
      "commissioningCustomFlowUrl": "",
      "commissioningModeInitialStepsHint": 0,
      "commissioningModeInitialStepsInstruction": "",
      "commissioningModeSecondaryStepsHint": 0,
      "commissioningModeSecondaryStepsInstruction": "",
      "userManualUrl": "",
      "supportUrl": "",
      "productUrl": "",
      "lsfUrl": "",
      "lsfRevision": 0,
      "creator": "cosmos1ynw4zl6xqnvh5zhzhhpxjc6kt8z8wvxkp8edsw"
    },
    {
      "vid": 5120,
      "pid": 1307,
      "deviceTypeId": 266,
      "productName": "Smart Home Plug",
      "productLabel": "M05X-P-3C",
      "partNumber": "M05X-P-3C",
      "commissioningCustomFlow": 0,
      "commissioningCustomFlowUrl": "",
      "commissioningModeInitialStepsHint": 0,
      "commissioningModeInitialStepsInstruction": "",
      "commissioningModeSecondaryStepsHint": 0,
      "commissioningModeSecondaryStepsInstruction": "",
      "userManualUrl": "",
      "supportUrl": "",
      "productUrl": "",
      "lsfUrl": "",
      "lsfRevision": 0,
      "creator": "cosmos1ynw4zl6xqnvh5zhzhhpxjc6kt8z8wvxkp8edsw"
    },
    {
      "vid": 5120,
      "pid": 1308,
      "deviceTypeId": 266,
      "productName": "Smart Home Plug",
      "productLabel": "M05X-P-3D",
      "partNumber": "M05X-P-3D",
      "commissioningCustomFlow": 0,
      "commissioningCustomFlowUrl": "",
      "commissioningModeInitialStepsHint": 0,
      "commissioningModeInitialStepsInstruction": "",
      "commissioningModeSecondaryStepsHint": 0,
      "commissioningModeSecondaryStepsInstruction": "",
      "userManualUrl": "",
      "supportUrl": "",
      "productUrl": "",
      "lsfUrl": "",
      "lsfRevision": 0,
      "creator": "cosmos1ynw4zl6xqnvh5zhzhhpxjc6kt8z8wvxkp8edsw"
    },
    {
      "vid": 5120,
      "pid": 1309,
      "deviceTypeId": 266,
      "productName": "Smart Home Plug",
      "productLabel": "M05X-P-3E",
      "partNumber": "M05X-P-3E",
      "commissioningCustomFlow": 0,
      "commissioningCustomFlowUrl": "",
      "commissioningModeInitialStepsHint": 0,
      "commissioningModeInitialStepsInstruction": "",
      "commissioningModeSecondaryStepsHint": 0,
      "commissioningModeSecondaryStepsInstruction": "",
      "userManualUrl": "",
      "supportUrl": "",
      "productUrl": "",
      "lsfUrl": "",
      "lsfRevision": 0,
      "creator": "cosmos1ynw4zl6xqnvh5zhzhhpxjc6kt8z8wvxkp8edsw"
    },
    {
      "vid": 5120,
      "pid": 1310,
      "deviceTypeId": 266,
      "productName": "Smart Home Plug",
      "productLabel": "M05X-P-3F",
      "partNumber": "M05X-P-3F",
      "commissioningCustomFlow": 0,
      "commissioningCustomFlowUrl": "",
      "commissioningModeInitialStepsHint": 0,
      "commissioningModeInitialStepsInstruction": "",
      "commissioningModeSecondaryStepsHint": 0,
      "commissioningModeSecondaryStepsInstruction": "",
      "userManualUrl": "",
      "supportUrl": "",
      "productUrl": "",
      "lsfUrl": "",
      "lsfRevision": 0,
      "creator": "cosmos1ynw4zl6xqnvh5zhzhhpxjc6kt8z8wvxkp8edsw"
    },
    {
      "vid": 5120,
      "pid": 1311,
      "deviceTypeId": 266,
      "productName": "Smart Home Plug",
      "productLabel": "M05X-P-40",
      "partNumber": "M05X-P-40",
      "commissioningCustomFlow": 0,
      "commissioningCustomFlowUrl": "",
      "commissioningModeInitialStepsHint": 0,
      "commissioningModeInitialStepsInstruction": "",
      "commissioningModeSecondaryStepsHint": 0,
      "commissioningModeSecondaryStepsInstruction": "",
      "userManualUrl": "",
      "supportUrl": "",
      "productUrl": "",
      "lsfUrl": "",
      "lsfRevision": 0,
      "creator": "cosmos1ynw4zl6xqnvh5zhzhhpxjc6kt8z8wvxkp8edsw"
    },
    {
      "vid": 5120,
      "pid": 1312,
      "deviceTypeId": 266,
      "productName": "Smart Home Plug",
      "productLabel": "M05X-P-41",
      "partNumber": "M05X-P-41",
      "commissioningCustomFlow": 0,
      "commissioningCustomFlowUrl": "",
      "commissioningModeInitialStepsHint": 0,
      "commissioningModeInitialStepsInstruction": "",
      "commissioningModeSecondaryStepsHint": 0,
      "commissioningModeSecondaryStepsInstruction": "",
      "userManualUrl": "",
      "supportUrl": "",
      "productUrl": "",
      "lsfUrl": "",
      "lsfRevision": 0,
      "creator": "cosmos1ynw4zl6xqnvh5zhzhhpxjc6kt8z8wvxkp8edsw"
    },
    {
      "vid": 5120,
      "pid": 1313,
      "deviceTypeId": 266,
      "productName": "Smart Home Plug",
      "productLabel": "M05X-P-42",
      "partNumber": "M05X-P-42",
      "commissioningCustomFlow": 0,
      "commissioningCustomFlowUrl": "",
      "commissioningModeInitialStepsHint": 0,
      "commissioningModeInitialStepsInstruction": "",
      "commissioningModeSecondaryStepsHint": 0,
      "commissioningModeSecondaryStepsInstruction": "",
      "userManualUrl": "",
      "supportUrl": "",
      "productUrl": "",
      "lsfUrl": "",
      "lsfRevision": 0,
      "creator": "cosmos1ynw4zl6xqnvh5zhzhhpxjc6kt8z8wvxkp8edsw"
    },
    {
      "vid": 5120,
      "pid": 1314,
      "deviceTypeId": 266,
      "productName": "Smart Home Plug",
      "productLabel": "M05X-P-43",
      "partNumber": "M05X-P-43",
      "commissioningCustomFlow": 0,
      "commissioningCustomFlowUrl": "",
      "commissioningModeInitialStepsHint": 0,
      "commissioningModeInitialStepsInstruction": "",
      "commissioningModeSecondaryStepsHint": 0,
      "commissioningModeSecondaryStepsInstruction": "",
      "userManualUrl": "",
      "supportUrl": "",
      "productUrl": "",
      "lsfUrl": "",
      "lsfRevision": 0,
      "creator": "cosmos1ynw4zl6xqnvh5zhzhhpxjc6kt8z8wvxkp8edsw"
    },
    {
      "vid": 5120,
      "pid": 1315,
      "deviceTypeId": 266,
      "productName": "Smart Home Plug",
      "productLabel": "M05X-P-44",
      "partNumber": "M05X-P-44",
      "commissioningCustomFlow": 0,
      "commissioningCustomFlowUrl": "",
      "commissioningModeInitialStepsHint": 0,
      "commissioningModeInitialStepsInstruction": "",
      "commissioningModeSecondaryStepsHint": 0,
      "commissioningModeSecondaryStepsInstruction": "",
      "userManualUrl": "",
      "supportUrl": "",
      "productUrl": "",
      "lsfUrl": "",
      "lsfRevision": 0,
      "creator": "cosmos1ynw4zl6xqnvh5zhzhhpxjc6kt8z8wvxkp8edsw"
    },
    {
      "vid": 5120,
      "pid": 1316,
      "deviceTypeId": 266,
      "productName": "Smart Home Plug",
      "productLabel": "M05X-P-45",
      "partNumber": "M05X-P-45",
      "commissioningCustomFlow": 0,
      "commissioningCustomFlowUrl": "",
      "commissioningModeInitialStepsHint": 0,
      "commissioningModeInitialStepsInstruction": "",
      "commissioningModeSecondaryStepsHint": 0,
      "commissioningModeSecondaryStepsInstruction": "",
      "userManualUrl": "",
      "supportUrl": "",
      "productUrl": "",
      "lsfUrl": "",
      "lsfRevision": 0,
      "creator": "cosmos1ynw4zl6xqnvh5zhzhhpxjc6kt8z8wvxkp8edsw"
    },
    {
      "vid": 5120,
      "pid": 1317,
      "deviceTypeId": 266,
      "productName": "Smart Home Plug",
      "productLabel": "M05X-P-46",
      "partNumber": "M05X-P-46",
      "commissioningCustomFlow": 0,
      "commissioningCustomFlowUrl": "",
      "commissioningModeInitialStepsHint": 0,
      "commissioningModeInitialStepsInstruction": "",
      "commissioningModeSecondaryStepsHint": 0,
      "commissioningModeSecondaryStepsInstruction": "",
      "userManualUrl": "",
      "supportUrl": "",
      "productUrl": "",
      "lsfUrl": "",
      "lsfRevision": 0,
      "creator": "cosmos1ynw4zl6xqnvh5zhzhhpxjc6kt8z8wvxkp8edsw"
    },
    {
      "vid": 5120,
      "pid": 1318,
      "deviceTypeId": 266,
      "productName": "Smart Home Plug",
      "productLabel": "M05X-P-47",
      "partNumber": "M05X-P-47",
      "commissioningCustomFlow": 0,
      "commissioningCustomFlowUrl": "",
      "commissioningModeInitialStepsHint": 0,
      "commissioningModeInitialStepsInstruction": "",
      "commissioningModeSecondaryStepsHint": 0,
      "commissioningModeSecondaryStepsInstruction": "",
      "userManualUrl": "",
      "supportUrl": "",
      "productUrl": "",
      "lsfUrl": "",
      "lsfRevision": 0,
      "creator": "cosmos1ynw4zl6xqnvh5zhzhhpxjc6kt8z8wvxkp8edsw"
    },
    {
      "vid": 5120,
      "pid": 1319,
      "deviceTypeId": 266,
      "productName": "Smart Home Plug",
      "productLabel": "M05X-P-48",
      "partNumber": "M05X-P-48",
      "commissioningCustomFlow": 0,
      "commissioningCustomFlowUrl": "",
      "commissioningModeInitialStepsHint": 0,
      "commissioningModeInitialStepsInstruction": "",
      "commissioningModeSecondaryStepsHint": 0,
      "commissioningModeSecondaryStepsInstruction": "",
      "userManualUrl": "",
      "supportUrl": "",
      "productUrl": "",
      "lsfUrl": "",
      "lsfRevision": 0,
      "creator": "cosmos1ynw4zl6xqnvh5zhzhhpxjc6kt8z8wvxkp8edsw"
    },
    {
      "vid": 5120,
      "pid": 1320,
      "deviceTypeId": 266,
      "productName": "Smart Home Plug",
      "productLabel": "M05X-P-49",
      "partNumber": "M05X-P-49",
      "commissioningCustomFlow": 0,
      "commissioningCustomFlowUrl": "",
      "commissioningModeInitialStepsHint": 0,
      "commissioningModeInitialStepsInstruction": "",
      "commissioningModeSecondaryStepsHint": 0,
      "commissioningModeSecondaryStepsInstruction": "",
      "userManualUrl": "",
      "supportUrl": "",
      "productUrl": "",
      "lsfUrl": "",
      "lsfRevision": 0,
      "creator": "cosmos1ynw4zl6xqnvh5zhzhhpxjc6kt8z8wvxkp8edsw"
    },
    {
      "vid": 5120,
      "pid": 1321,
      "deviceTypeId": 266,
      "productName": "Smart Home Plug",
      "productLabel": "M05X-P-4A",
      "partNumber": "M05X-P-4A",
      "commissioningCustomFlow": 0,
      "commissioningCustomFlowUrl": "",
      "commissioningModeInitialStepsHint": 0,
      "commissioningModeInitialStepsInstruction": "",
      "commissioningModeSecondaryStepsHint": 0,
      "commissioningModeSecondaryStepsInstruction": "",
      "userManualUrl": "",
      "supportUrl": "",
      "productUrl": "",
      "lsfUrl": "",
      "lsfRevision": 0,
      "creator": "cosmos1ynw4zl6xqnvh5zhzhhpxjc6kt8z8wvxkp8edsw"
    },
    {
      "vid": 5120,
      "pid": 1322,
      "deviceTypeId": 266,
      "productName": "Smart Home Plug",
      "productLabel": "M05X-P-4B",
      "partNumber": "M05X-P-4B",
      "commissioningCustomFlow": 0,
      "commissioningCustomFlowUrl": "",
      "commissioningModeInitialStepsHint": 0,
      "commissioningModeInitialStepsInstruction": "",
      "commissioningModeSecondaryStepsHint": 0,
      "commissioningModeSecondaryStepsInstruction": "",
      "userManualUrl": "",
      "supportUrl": "",
      "productUrl": "",
      "lsfUrl": "",
      "lsfRevision": 0,
      "creator": "cosmos1ynw4zl6xqnvh5zhzhhpxjc6kt8z8wvxkp8edsw"
    },
    {
      "vid": 5120,
      "pid": 1323,
      "deviceTypeId": 266,
      "productName": "Smart Home Plug",
      "productLabel": "M05X-P-4C",
      "partNumber": "M05X-P-4C",
      "commissioningCustomFlow": 0,
      "commissioningCustomFlowUrl": "",
      "commissioningModeInitialStepsHint": 0,
      "commissioningModeInitialStepsInstruction": "",
      "commissioningModeSecondaryStepsHint": 0,
      "commissioningModeSecondaryStepsInstruction": "",
      "userManualUrl": "",
      "supportUrl": "",
      "productUrl": "",
      "lsfUrl": "",
      "lsfRevision": 0,
      "creator": "cosmos1ynw4zl6xqnvh5zhzhhpxjc6kt8z8wvxkp8edsw"
    },
    {
      "vid": 5120,
      "pid": 1324,
      "deviceTypeId": 266,
      "productName": "Smart Home Plug",
      "productLabel": "M05X-P-4D",
      "partNumber": "M05X-P-4D",
      "commissioningCustomFlow": 0,
      "commissioningCustomFlowUrl": "",
      "commissioningModeInitialStepsHint": 0,
      "commissioningModeInitialStepsInstruction": "",
      "commissioningModeSecondaryStepsHint": 0,
      "commissioningModeSecondaryStepsInstruction": "",
      "userManualUrl": "",
      "supportUrl": "",
      "productUrl": "",
      "lsfUrl": "",
      "lsfRevision": 0,
      "creator": "cosmos1ynw4zl6xqnvh5zhzhhpxjc6kt8z8wvxkp8edsw"
    },
    {
      "vid": 5120,
      "pid": 1325,
      "deviceTypeId": 266,
      "productName": "Smart Home Plug",
      "productLabel": "M05X-P-4E",
      "partNumber": "M05X-P-4E",
      "commissioningCustomFlow": 0,
      "commissioningCustomFlowUrl": "",
      "commissioningModeInitialStepsHint": 0,
      "commissioningModeInitialStepsInstruction": "",
      "commissioningModeSecondaryStepsHint": 0,
      "commissioningModeSecondaryStepsInstruction": "",
      "userManualUrl": "",
      "supportUrl": "",
      "productUrl": "",
      "lsfUrl": "",
      "lsfRevision": 0,
      "creator": "cosmos1ynw4zl6xqnvh5zhzhhpxjc6kt8z8wvxkp8edsw"
    },
    {
      "vid": 5120,
      "pid": 1326,
      "deviceTypeId": 266,
      "productName": "Smart Home Plug",
      "productLabel": "M05X-P-4F",
      "partNumber": "M05X-P-4F",
      "commissioningCustomFlow": 0,
      "commissioningCustomFlowUrl": "",
      "commissioningModeInitialStepsHint": 0,
      "commissioningModeInitialStepsInstruction": "",
      "commissioningModeSecondaryStepsHint": 0,
      "commissioningModeSecondaryStepsInstruction": "",
      "userManualUrl": "",
      "supportUrl": "",
      "productUrl": "",
      "lsfUrl": "",
      "lsfRevision": 0,
      "creator": "cosmos1ynw4zl6xqnvh5zhzhhpxjc6kt8z8wvxkp8edsw"
    },
    {
      "vid": 5123,
      "pid": 404,
      "deviceTypeId": 269,
      "productName": "RGB CCT Dimmable LED A60 Globe ",
      "productLabel": "RGB CCT Dimmable LED A60 Globe ",
      "partNumber": "GLD322MTRHA",
      "commissioningCustomFlow": 0,
      "commissioningCustomFlowUrl": "",
      "commissioningModeInitialStepsHint": 0,
      "commissioningModeInitialStepsInstruction": "",
      "commissioningModeSecondaryStepsHint": 0,
      "commissioningModeSecondaryStepsInstruction": "",
      "userManualUrl": "",
      "supportUrl": "",
      "productUrl": "",
      "lsfUrl": "",
      "lsfRevision": 0,
      "creator": "cosmos1d9ut0ysdlw68r0705q8tagf7y9cf3d686fpf73"
    },
    {
      "vid": 5123,
      "pid": 408,
      "deviceTypeId": 269,
      "productName": "RGB CCT Dimmable LED Downlight",
      "productLabel": "RGB CCT Dimmable LED Downlight",
      "partNumber": "ALD095MTRHA",
      "commissioningCustomFlow": 0,
      "commissioningCustomFlowUrl": "",
      "commissioningModeInitialStepsHint": 0,
      "commissioningModeInitialStepsInstruction": "",
      "commissioningModeSecondaryStepsHint": 0,
      "commissioningModeSecondaryStepsInstruction": "",
      "userManualUrl": "",
      "supportUrl": "",
      "productUrl": "",
      "lsfUrl": "",
      "lsfRevision": 0,
      "creator": "cosmos1d9ut0ysdlw68r0705q8tagf7y9cf3d686fpf73"
    },
    {
      "vid": 5123,
      "pid": 1258,
      "deviceTypeId": 269,
      "productName": "RGB + W Dimmable LED Lightstrip",
      "productLabel": "RGB + W Dimmable LED Lightstrip",
      "partNumber": "ALD563MTRHA",
      "commissioningCustomFlow": 0,
      "commissioningCustomFlowUrl": "",
      "commissioningModeInitialStepsHint": 0,
      "commissioningModeInitialStepsInstruction": "",
      "commissioningModeSecondaryStepsHint": 0,
      "commissioningModeSecondaryStepsInstruction": "",
      "userManualUrl": "",
      "supportUrl": "",
      "productUrl": "",
      "lsfUrl": "",
      "lsfRevision": 0,
      "creator": "cosmos1d9ut0ysdlw68r0705q8tagf7y9cf3d686fpf73"
    },
    {
      "vid": 5123,
      "pid": 1323,
      "deviceTypeId": 266,
      "productName": "Single Plugin Socket",
      "productLabel": "Single Plugin Socket",
      "partNumber": "PC191MTRHA",
      "commissioningCustomFlow": 0,
      "commissioningCustomFlowUrl": "",
      "commissioningModeInitialStepsHint": 0,
      "commissioningModeInitialStepsInstruction": "",
      "commissioningModeSecondaryStepsHint": 0,
      "commissioningModeSecondaryStepsInstruction": "",
      "userManualUrl": "",
      "supportUrl": "",
      "productUrl": "",
      "lsfUrl": "",
      "lsfRevision": 0,
      "creator": "cosmos1d9ut0ysdlw68r0705q8tagf7y9cf3d686fpf73"
    },
    {
      "vid": 5124,
      "pid": 4101,
      "deviceTypeId": 269,
      "productName": "Smart Color Light",
      "productLabel": "Smart Color Light",
      "partNumber": "SCLA5",
      "commissioningCustomFlow": 0,
      "commissioningCustomFlowUrl": "",
      "commissioningModeInitialStepsHint": 0,
      "commissioningModeInitialStepsInstruction": "",
      "commissioningModeSecondaryStepsHint": 0,
      "commissioningModeSecondaryStepsInstruction": "",
      "userManualUrl": "",
      "supportUrl": "",
      "productUrl": "",
      "lsfUrl": "",
      "lsfRevision": 0,
      "creator": "cosmos1h4rf0hjzf498s2lu0rf8m52ujst2gl7lpdnexs"
    },
    {
      "vid": 5124,
      "pid": 32768,
      "deviceTypeId": 266,
      "productName": "Smart Wi-Fi Plug",
      "productLabel": "Smart Wi-Fi Plug",
      "partNumber": "SP-M",
      "commissioningCustomFlow": 0,
      "commissioningCustomFlowUrl": "",
      "commissioningModeInitialStepsHint": 0,
      "commissioningModeInitialStepsInstruction": "",
      "commissioningModeSecondaryStepsHint": 0,
      "commissioningModeSecondaryStepsInstruction": "",
      "userManualUrl": "",
      "supportUrl": "",
      "productUrl": "",
      "lsfUrl": "",
      "lsfRevision": 0,
      "creator": "cosmos1h4rf0hjzf498s2lu0rf8m52ujst2gl7lpdnexs"
    },
    {
      "vid": 5124,
      "pid": 32769,
      "deviceTypeId": 266,
      "productName": "Smart Wi-Fi Plug",
      "productLabel": "Smart Wi-Fi Plug",
      "partNumber": "WP3",
      "commissioningCustomFlow": 0,
      "commissioningCustomFlowUrl": "",
      "commissioningModeInitialStepsHint": 0,
      "commissioningModeInitialStepsInstruction": "",
      "commissioningModeSecondaryStepsHint": 0,
      "commissioningModeSecondaryStepsInstruction": "",
      "userManualUrl": "",
      "supportUrl": "",
      "productUrl": "",
      "lsfUrl": "",
      "lsfRevision": 0,
      "creator": "cosmos1h4rf0hjzf498s2lu0rf8m52ujst2gl7lpdnexs"
    },
    {
      "vid": 5125,
      "pid": 1,
      "deviceTypeId": 116,
      "productName": "Floor Cleaning Robot",
      "productLabel": "Floor Cleaning Robot",
      "partNumber": "-",
      "commissioningCustomFlow": 0,
      "commissioningCustomFlowUrl": "",
      "commissioningModeInitialStepsHint": 0,
      "commissioningModeInitialStepsInstruction": "",
      "commissioningModeSecondaryStepsHint": 0,
      "commissioningModeSecondaryStepsInstruction": "",
      "userManualUrl": "",
      "supportUrl": "",
      "productUrl": "",
      "lsfUrl": "",
      "lsfRevision": 0,
      "creator": "cosmos1z4c6z3ppegtqvlrp83v3alpnguw7yygqyd2788"
    },
    {
      "vid": 5127,
      "pid": 4232,
      "deviceTypeId": 269,
      "productName": "Smart Color Night Light",
      "productLabel": "Smart Night Light-W",
      "partNumber": "3RSNL02041WM",
      "commissioningCustomFlow": 0,
      "commissioningCustomFlowUrl": "",
      "commissioningModeInitialStepsHint": 0,
      "commissioningModeInitialStepsInstruction": "",
      "commissioningModeSecondaryStepsHint": 0,
      "commissioningModeSecondaryStepsInstruction": "",
      "userManualUrl": "",
      "supportUrl": "",
      "productUrl": "",
      "lsfUrl": "",
      "lsfRevision": 0,
      "creator": "cosmos1qwnh6tj4n938g3fmncqna22zmfxx50vnd22yux"
    },
    {
      "vid": 5127,
      "pid": 4233,
      "deviceTypeId": 269,
      "productName": "Smart Color Bulb ML1",
      "productLabel": "Smart Color Bulb Light ",
      "partNumber": "3RCB01051W",
      "commissioningCustomFlow": 0,
      "commissioningCustomFlowUrl": "",
      "commissioningModeInitialStepsHint": 0,
      "commissioningModeInitialStepsInstruction": "",
      "commissioningModeSecondaryStepsHint": 0,
      "commissioningModeSecondaryStepsInstruction": "",
      "userManualUrl": "",
      "supportUrl": "",
      "productUrl": "",
      "lsfUrl": "",
      "lsfRevision": 0,
      "creator": "cosmos1qwnh6tj4n938g3fmncqna22zmfxx50vnd22yux"
    },
    {
      "vid": 5127,
      "pid": 4488,
      "deviceTypeId": 266,
      "productName": "Smart WiFi Plug",
      "productLabel": "Smart Wi-Fi Plug",
      "partNumber": "3RSP03046W",
      "commissioningCustomFlow": 0,
      "commissioningCustomFlowUrl": "",
      "commissioningModeInitialStepsHint": 0,
      "commissioningModeInitialStepsInstruction": "",
      "commissioningModeSecondaryStepsHint": 0,
      "commissioningModeSecondaryStepsInstruction": "",
      "userManualUrl": "",
      "supportUrl": "",
      "productUrl": "",
      "lsfUrl": "",
      "lsfRevision": 0,
      "creator": "cosmos1qwnh6tj4n938g3fmncqna22zmfxx50vnd22yux"
    },
    {
      "vid": 5127,
      "pid": 4744,
      "deviceTypeId": 14,
      "productName": "Smart Bridge MZ1",
      "productLabel": "Matter Zigbee Bridge",
      "partNumber": "3RMB01033WBZ",
      "commissioningCustomFlow": 0,
      "commissioningCustomFlowUrl": "",
      "commissioningModeInitialStepsHint": 0,
      "commissioningModeInitialStepsInstruction": "",
      "commissioningModeSecondaryStepsHint": 0,
      "commissioningModeSecondaryStepsInstruction": "",
      "userManualUrl": "",
      "supportUrl": "",
      "productUrl": "",
      "lsfUrl": "",
      "lsfRevision": 0,
      "creator": "cosmos1qwnh6tj4n938g3fmncqna22zmfxx50vnd22yux"
    },
    {
      "vid": 5131,
      "pid": 32771,
      "deviceTypeId": 10,
      "productName": "Anona Holo",
      "productLabel": "Anona Holo",
      "partNumber": "-",
      "commissioningCustomFlow": 0,
      "commissioningCustomFlowUrl": "",
      "commissioningModeInitialStepsHint": 0,
      "commissioningModeInitialStepsInstruction": "",
      "commissioningModeSecondaryStepsHint": 0,
      "commissioningModeSecondaryStepsInstruction": "",
      "userManualUrl": "",
      "supportUrl": "",
      "productUrl": "",
      "lsfUrl": "",
      "lsfRevision": 0,
      "creator": "cosmos16eywj3z0k6jaxnuycky4k7u2m8wt7qy9wclxv4"
    },
    {
      "vid": 5136,
      "pid": 1000,
      "deviceTypeId": 256,
      "productName": "On/Off Light",
      "productLabel": "Matter On/Off Light",
      "partNumber": "PMOL1001",
      "commissioningCustomFlow": 0,
      "commissioningCustomFlowUrl": "",
      "commissioningModeInitialStepsHint": 0,
      "commissioningModeInitialStepsInstruction": "",
      "commissioningModeSecondaryStepsHint": 0,
      "commissioningModeSecondaryStepsInstruction": "",
      "userManualUrl": "",
      "supportUrl": "",
      "productUrl": "",
      "lsfUrl": "",
      "lsfRevision": 0,
      "creator": "cosmos1dqrg6w2jjs7sft59dpqngjzyfdjh4xjn5rjct5"
    },
    {
      "vid": 5136,
      "pid": 1001,
      "deviceTypeId": 269,
      "productName": "Extended Color Light",
      "productLabel": "Matter Extended Color Light",
      "partNumber": "PMECL1000",
      "commissioningCustomFlow": 0,
      "commissioningCustomFlowUrl": "",
      "commissioningModeInitialStepsHint": 0,
      "commissioningModeInitialStepsInstruction": "",
      "commissioningModeSecondaryStepsHint": 0,
      "commissioningModeSecondaryStepsInstruction": "",
      "userManualUrl": "",
      "supportUrl": "",
      "productUrl": "",
      "lsfUrl": "",
      "lsfRevision": 0,
      "creator": "cosmos1dqrg6w2jjs7sft59dpqngjzyfdjh4xjn5rjct5"
    },
    {
      "vid": 5136,
      "pid": 1002,
      "deviceTypeId": 266,
      "productName": "On/off Plug-in Unit",
      "productLabel": "Matter On/off Plug-in Unit",
      "partNumber": "PMOPU1002",
      "commissioningCustomFlow": 0,
      "commissioningCustomFlowUrl": "",
      "commissioningModeInitialStepsHint": 0,
      "commissioningModeInitialStepsInstruction": "",
      "commissioningModeSecondaryStepsHint": 0,
      "commissioningModeSecondaryStepsInstruction": "",
      "userManualUrl": "",
      "supportUrl": "",
      "productUrl": "",
      "lsfUrl": "",
      "lsfRevision": 0,
      "creator": "cosmos1dqrg6w2jjs7sft59dpqngjzyfdjh4xjn5rjct5"
    },
    {
      "vid": 5136,
      "pid": 1003,
      "deviceTypeId": 259,
      "productName": "On/off Light Switch",
      "productLabel": "Matter On/off Light Switch",
      "partNumber": "PMOLS1003",
      "commissioningCustomFlow": 0,
      "commissioningCustomFlowUrl": "",
      "commissioningModeInitialStepsHint": 0,
      "commissioningModeInitialStepsInstruction": "",
      "commissioningModeSecondaryStepsHint": 0,
      "commissioningModeSecondaryStepsInstruction": "",
      "userManualUrl": "",
      "supportUrl": "",
      "productUrl": "",
      "lsfUrl": "",
      "lsfRevision": 0,
      "creator": "cosmos1dqrg6w2jjs7sft59dpqngjzyfdjh4xjn5rjct5"
    }
  ],
  "pagination": {
    "next_key": "AAAUEC8AAAPsLw==",
    "total": "0"
  }
}
